{
  "ok": true,
  "text": "blue",
  "source": "english",
  "target": "portuguese",
  "translations": [
    "picante",
    "",
    "",
    "",
    "indecente",
    "",
    "",
    "",
    "",
    "azular",
    "",
    "",
    "",
    "",
    "lívido"
  ],
  "examples": [
    {
      "id": 0,
      "source": "The blue team won by a long way in the annual sports day.",
      "target": "O time azul venceu de longe no dia esportivo anual."
    },
    {
      "id": 1,
      "source": "The painting had a hint of blue that drew my eye.",
      "target": "A pintura tinha uma nuance de azul que atraía meu olhar."
    },
    {
      "id": 2,
      "source": "He wore a blue smile that hinted at his hidden sorrows.",
      "target": "Ele exibia um sorriso triste que sugeria suas mágoas ocultas."
    },
    {
      "id": 3,
      "source": "She will most likely choose the blue dress for the event.",
      "target": "É provável que ela escolha o vestido azul para o evento."
    },
    {
      "id": 4,
      "source": "The blue whale is by far the largest animal to have ever existed.",
      "target": "A baleia azul é, de longe, o maior animal que já existiu."
    },
    {
      "id": 5,
      "source": "His bright blue hair turned heads as he walked through the mall.",
      "target": "Seu cabelo azul brilhante deu nas vistas enquanto ele caminhava pelo shopping."
    },
    {
      "id": 6,
      "source": "He wore a dusk shade of blue that complemented his eyes.",
      "target": "Ele vestia um tom de azul sombreado que realçava seus olhos."
    },
    {
      "id": 7,
      "source": "This painting has a beautiful blend of blue and orange hues.",
      "target": "Esta pintura tem uma bela mistura de tons azuis e alaranjados."
    },
    {
      "id": 8,
      "source": "He complemented the room's decor with a bright blue throw.",
      "target": "Ele complementou a decoração do quarto com uma manta azul brilhante."
    },
    {
      "id": 9,
      "source": "The sparkling blue ocean set apart this beach from all the others.",
      "target": "O oceano azul cintilante destacou esta praia de todas as outras."
    },
    {
      "id": 10,
      "source": "The scenic view was dominated by tranquil open water and blue skies.",
      "target": "A vista panorâmica era dominada por águas abertas e céus azuis tranquilos."
    },
    {
      "id": 11,
      "source": "He painted his room a calming shade of blue for relaxation.",
      "target": "Ele pintou seu quarto com um tom relaxante de azul para descansar."
    },
    {
      "id": 12,
      "source": "Her notebook had a beautiful blue cover with floral designs.",
      "target": "Seu caderno tinha uma linda capa azul com desenhos florais."
    },
    {
      "id": 13,
      "source": "The artist used blue to symbolize peace in his painting.",
      "target": "O artista usou o azul para simbolizar a paz em sua pintura."
    },
    {
      "id": 14,
      "source": "The lake appeared a vibrant blue against the green landscape.",
      "target": "O lago parecia de um azul vibrante contra a paisagem verde."
    },
    {
      "id": 15,
      "source": "They painted the fence a fresh blue to update the garden.",
      "target": "Eles pintaram a cerca de um azul fresco para renovar o jardim."
    },
    {
      "id": 16,
      "source": "We chose blue curtains to match the light color of the walls.",
      "target": "Escolhemos cortinas azuis para combinar com a cor clara das paredes."
    },
    {
      "id": 17,
      "source": "Look at that blue dress; it is perfect for summer outings.",
      "target": "Olhe aquele vestido azul; é perfeito para passeios de verão."
    },
    {
      "id": 18,
      "source": "The blue in the flag symbolizes loyalty and peace in our nation.",
      "target": "O azul na bandeira simboliza lealdade e paz em nossa nação."
    },
    {
      "id": 19,
      "source": "My favorite drink comes in a blue can with a cool design.",
      "target": "Minha bebida favorita vem numa lata azul com um design legal."
    }
  ]
}